rtl/peripherals/uart.v
/**
 * @file uart.v
 * @brief Simple UART Peripheral for Debug and Communication
 *
 * Provides basic UART functionality with configurable baud rate.
 * Standard 8N1 format (8 data bits, no parity, 1 stop bit).
 *
 * Features:
 * - Configurable baud rate via clock divider
 * - 8N1 format (8 data, no parity, 1 stop)
 * - TX and RX with status flags
 * - Interrupt on RX data ready
 * - Simple buffering (1-byte TX/RX)
 *
 * Register Map (Base: 0x00020500):
 * 0x00: DATA        - TX/RX data register
 * 0x04: STATUS      - Status register (TX_EMPTY, RX_READY, etc.)
 * 0x08: CTRL        - Control register (enable, interrupt enable)
 * 0x0C: BAUD_DIV    - Baud rate divider (CLK / BAUD_DIV = baud rate)
 *
 * STATUS Register:
 * [0]: RX_READY     - Receive data available
 * [1]: TX_EMPTY     - Transmit buffer empty
 * [2]: RX_OVERRUN   - Receive overrun error
 * [3]: FRAME_ERROR  - Frame error detected
 * [7:4]: Reserved
 *
 * CTRL Register:
 * [0]: RX_ENABLE    - Enable receiver
 * [1]: TX_ENABLE    - Enable transmitter
 * [2]: RX_INT_EN    - Enable RX interrupt
 * [7:3]: Reserved
 *
 * Baud Rate Calculation:
 * BAUD_DIV = CLK_FREQ / BAUD_RATE
 * Example: 50 MHz / 115200 = 434
 */

module uart #(
    parameter ADDR_WIDTH = 8,
    parameter CLK_FREQ = 50_000_000,
    parameter DEFAULT_BAUD = 115200
)(
    // Wishbone bus interface
    input  wire                    clk,
    input  wire                    rst_n,
    input  wire [ADDR_WIDTH-1:0]   wb_addr,
    input  wire [31:0]             wb_dat_i,
    output reg  [31:0]             wb_dat_o,
    input  wire                    wb_we,
    input  wire [3:0]              wb_sel,
    input  wire                    wb_stb,
    output reg                     wb_ack,

    // UART interface
    input  wire                    uart_rx,
    output reg                     uart_tx,

    // Interrupt
    output reg                     irq
);

    //==========================================================================
    // Control Registers
    //==========================================================================

    localparam DEFAULT_BAUD_DIV = CLK_FREQ / DEFAULT_BAUD;

    reg        rx_enable;
    reg        tx_enable;
    reg        rx_int_en;
    reg [15:0] baud_div;
    reg [7:0]  tx_data;
    reg [7:0]  rx_data;
    reg        rx_ready;
    reg        tx_empty;
    reg        rx_overrun;
    reg        frame_error;

    // Initialize
    initial begin
        rx_enable = 1'b1;
        tx_enable = 1'b1;
        rx_int_en = 1'b0;
        baud_div = DEFAULT_BAUD_DIV;
        tx_data = 8'd0;
        rx_data = 8'd0;
        rx_ready = 1'b0;
        tx_empty = 1'b1;
        rx_overrun = 1'b0;
        frame_error = 1'b0;
        uart_tx = 1'b1;
        irq = 1'b0;
    end

    //==========================================================================
    // TX State Machine
    //==========================================================================

    localparam TX_IDLE  = 2'd0;
    localparam TX_START = 2'd1;
    localparam TX_DATA  = 2'd2;
    localparam TX_STOP  = 2'd3;

    reg [1:0]  tx_state;
    reg [15:0] tx_baud_counter;
    reg [2:0]  tx_bit_counter;
    reg [7:0]  tx_shift_reg;
    reg        tx_start;

    always @(posedge clk or negedge rst_n) begin
        if (!rst_n) begin
            tx_state <= TX_IDLE;
            uart_tx <= 1'b1;
            tx_baud_counter <= 16'd0;
            tx_bit_counter <= 3'd0;
            tx_shift_reg <= 8'd0;
            tx_empty <= 1'b1;
        end else begin
            case (tx_state)
                TX_IDLE: begin
                    uart_tx <= 1'b1;
                    // tx_empty is set in TX_STOP when transmission completes
                    // Removed race condition: was setting tx_empty=1 every cycle here
                    tx_baud_counter <= 16'd0;

                    if (tx_enable && tx_start) begin
                        tx_state <= TX_START;
                        tx_shift_reg <= tx_data;
                        tx_empty <= 1'b0;
                    end
                end

                TX_START: begin
                    uart_tx <= 1'b0;  // Start bit
                    tx_baud_counter <= tx_baud_counter + 1;

                    if (tx_baud_counter >= baud_div - 1) begin
                        tx_state <= TX_DATA;
                        tx_baud_counter <= 16'd0;
                        tx_bit_counter <= 3'd0;
                        uart_tx <= tx_shift_reg[0];  // Set first data bit
                    end
                end

                TX_DATA: begin
                    // Set uart_tx to current bit every cycle (holds value stable)
                    uart_tx <= tx_shift_reg[0];
                    tx_baud_counter <= tx_baud_counter + 1;

                    if (tx_baud_counter >= baud_div - 1) begin
                        tx_shift_reg <= {1'b0, tx_shift_reg[7:1]};
                        tx_bit_counter <= tx_bit_counter + 1;
                        tx_baud_counter <= 16'd0;

                        if (tx_bit_counter == 7) begin
                            tx_state <= TX_STOP;
                        end
                        // Note: uart_tx is set every cycle to tx_shift_reg[0]
                        // After shift, next bit is automatically in position [0]
                    end
                end

                TX_STOP: begin
                    uart_tx <= 1'b1;  // Stop bit
                    tx_baud_counter <= tx_baud_counter + 1;

                    if (tx_baud_counter >= baud_div - 1) begin
                        tx_state <= TX_IDLE;
                        tx_baud_counter <= 16'd0;
                        tx_empty <= 1'b1;  // Set tx_empty when transmission completes
                    end
                end
            endcase
        end
    end

    //==========================================================================
    // RX State Machine
    //==========================================================================

    localparam RX_IDLE  = 2'd0;
    localparam RX_START = 2'd1;
    localparam RX_DATA  = 2'd2;
    localparam RX_STOP  = 2'd3;

    reg [1:0]  rx_state;
    reg [15:0] rx_baud_counter;
    reg [2:0]  rx_bit_counter;
    reg [7:0]  rx_shift_reg;
    reg        uart_rx_sync1;
    reg        uart_rx_sync2;

    // Synchronize RX input (prevent metastability)
    always @(posedge clk or negedge rst_n) begin
        if (!rst_n) begin
            uart_rx_sync1 <= 1'b1;
            uart_rx_sync2 <= 1'b1;
        end else begin
            uart_rx_sync1 <= uart_rx;
            uart_rx_sync2 <= uart_rx_sync1;
        end
    end

    always @(posedge clk or negedge rst_n) begin
        if (!rst_n) begin
            rx_state <= RX_IDLE;
            rx_baud_counter <= 16'd0;
            rx_bit_counter <= 3'd0;
            rx_shift_reg <= 8'd0;
            rx_ready <= 1'b0;
            rx_overrun <= 1'b0;
            frame_error <= 1'b0;
        end else begin
            case (rx_state)
                RX_IDLE: begin
                    rx_baud_counter <= 16'd0;

                    if (rx_enable && !uart_rx_sync2) begin
                        // Falling edge detected (start bit)
                        rx_state <= RX_START;
                    end
                end

                RX_START: begin
                    rx_baud_counter <= rx_baud_counter + 1;

                    // Sample at middle of bit period
                    if (rx_baud_counter >= (baud_div >> 1)) begin
                        if (!uart_rx_sync2) begin
                            // Valid start bit
                            rx_state <= RX_DATA;
                            rx_baud_counter <= 16'd0;
                            rx_bit_counter <= 3'd0;
                        end else begin
                            // False start bit
                            rx_state <= RX_IDLE;
                        end
                    end
                end

                RX_DATA: begin
                    rx_baud_counter <= rx_baud_counter + 1;

                    if (rx_baud_counter >= baud_div - 1) begin
                        rx_shift_reg <= {uart_rx_sync2, rx_shift_reg[7:1]};
                        rx_bit_counter <= rx_bit_counter + 1;
                        rx_baud_counter <= 16'd0;

                        if (rx_bit_counter == 7) begin
                            rx_state <= RX_STOP;
                        end
                    end
                end

                RX_STOP: begin
                    rx_baud_counter <= rx_baud_counter + 1;

                    if (rx_baud_counter >= baud_div - 1) begin
                        if (uart_rx_sync2) begin
                            // Valid stop bit
                            if (rx_ready) begin
                                rx_overrun <= 1'b1;  // Previous data not read
                            end else begin
                                rx_data <= rx_shift_reg;
                                rx_ready <= 1'b1;
                            end
                        end else begin
                            frame_error <= 1'b1;  // Invalid stop bit
                        end
                        rx_state <= RX_IDLE;
                        rx_baud_counter <= 16'd0;
                    end
                end
            endcase
        end
    end

    // Generate interrupt
    always @(posedge clk or negedge rst_n) begin
        if (!rst_n) begin
            irq <= 1'b0;
        end else begin
            irq <= rx_int_en && rx_ready;
        end
    end

    //==========================================================================
    // Wishbone Bus Interface
    //==========================================================================

    always @(posedge clk or negedge rst_n) begin
        if (!rst_n) begin
            rx_enable <= 1'b1;
            tx_enable <= 1'b1;
            rx_int_en <= 1'b0;
            baud_div <= DEFAULT_BAUD_DIV;
            tx_start <= 1'b0;
            wb_ack <= 1'b0;
            wb_dat_o <= 32'd0;
        end else begin
            wb_ack <= wb_stb && !wb_ack;
            tx_start <= 1'b0;  // Self-clearing

            if (wb_stb && wb_we && !wb_ack) begin
                // Write
                case (wb_addr[7:2])
                    6'h00: begin  // DATA
                        tx_data <= wb_dat_i[7:0];
                        tx_start <= 1'b1;
                    end
                    6'h02: begin  // CTRL
                        rx_enable <= wb_dat_i[0];
                        tx_enable <= wb_dat_i[1];
                        rx_int_en <= wb_dat_i[2];
                    end
                    6'h03: baud_div <= wb_dat_i[15:0];  // BAUD_DIV
                endcase
            end else if (wb_stb && !wb_we && !wb_ack) begin
                // Read
                case (wb_addr[7:2])
                    6'h00: begin  // DATA
                        wb_dat_o <= {24'd0, rx_data};
                        rx_ready <= 1'b0;     // Clear RX_READY on read
                        rx_overrun <= 1'b0;   // Clear errors
                        frame_error <= 1'b0;
                    end
                    6'h01: begin  // STATUS
                        wb_dat_o <= {28'd0, frame_error, rx_overrun, tx_empty, rx_ready};
                    end
                    6'h02: wb_dat_o <= {29'd0, rx_int_en, tx_enable, rx_enable};  // CTRL
                    6'h03: wb_dat_o <= {16'd0, baud_div};  // BAUD_DIV
                    default: wb_dat_o <= 32'h0;
                endcase
            end
        end
    end

endmodule

sim/test_uart_simple.v
`timescale 1ns/1ps

// Simple standalone UART test
module test_uart_simple;

reg clk, rst_n;
reg [7:0] wb_addr;
reg [31:0] wb_dat_i;
wire [31:0] wb_dat_o;
reg wb_we;
reg [3:0] wb_sel;
reg wb_stb;
wire wb_ack;
wire uart_tx;
wire irq;

// Instantiate UART
uart #(
    .ADDR_WIDTH(8),
    .CLK_FREQ(50_000_000),
    .DEFAULT_BAUD(115200)
) dut (
    .clk(clk),
    .rst_n(rst_n),
    .wb_addr(wb_addr),
    .wb_dat_i(wb_dat_i),
    .wb_dat_o(wb_dat_o),
    .wb_we(wb_we),
    .wb_sel(wb_sel),
    .wb_stb(wb_stb),
    .wb_ack(wb_ack),
    .uart_rx(1'b1),
    .uart_tx(uart_tx),
    .irq(irq)
);

// Clock
initial begin
    clk = 0;
    forever #10 clk = ~clk;  // 50 MHz
end

// Test
initial begin
    $dumpfile("test_uart_simple.vcd");
    $dumpvars(0, test_uart_simple);

    // Reset
    rst_n = 0;
    wb_addr = 0;
    wb_dat_i = 0;
    wb_we = 0;
    wb_sel = 4'hF;
    wb_stb = 0;
    #100;
    rst_n = 1;
    #100;

    $display("=== Writing 0x48 ('H') to UART ===");
    // Write data
    @(posedge clk);
    wb_addr = 8'h00;  // DATA register
    wb_dat_i = 32'h00000048;  // 'H'
    wb_we = 1'b1;
    wb_stb = 1'b1;

    // Wait for ack
    @(posedge clk);
    while (!wb_ack) @(posedge clk);

    // Deassert
    wb_stb = 1'b0;
    wb_we = 1'b0;

    // Wait for transmission to complete
    #200000;

    $display("=== Test complete ===");
    $finish;
end

endmodule

sim/test_uart_simple.vcd
$date
	Sat Dec 13 23:57:24 2025
$end
$version
	Icarus Verilog
$end
$timescale
	1ps
$end
$scope module test_uart_simple $end
$var wire 32 ! wb_dat_o [31:0] $end
$var wire 1 " wb_ack $end
$var wire 1 # uart_tx $end
$var wire 1 $ irq $end
$var reg 1 % clk $end
$var reg 1 & rst_n $end
$var reg 8 ' wb_addr [7:0] $end
$var reg 32 ( wb_dat_i [31:0] $end
$var reg 4 ) wb_sel [3:0] $end
$var reg 1 * wb_stb $end
$var reg 1 + wb_we $end
$scope module dut $end
$var wire 1 % clk $end
$var wire 1 & rst_n $end
$var wire 1 , uart_rx $end
$var wire 8 - wb_addr [7:0] $end
$var wire 32 . wb_dat_i [31:0] $end
$var wire 4 / wb_sel [3:0] $end
$var wire 1 * wb_stb $end
$var wire 1 + wb_we $end
$var parameter 32 0 ADDR_WIDTH $end
$var parameter 32 1 CLK_FREQ $end
$var parameter 32 2 DEFAULT_BAUD $end
$var parameter 32 3 DEFAULT_BAUD_DIV $end
$var parameter 2 4 RX_DATA $end
$var parameter 2 5 RX_IDLE $end
$var parameter 2 6 RX_START $end
$var parameter 2 7 RX_STOP $end
$var parameter 2 8 TX_DATA $end
$var parameter 2 9 TX_IDLE $end
$var parameter 2 : TX_START $end
$var parameter 2 ; TX_STOP $end
$var reg 16 < baud_div [15:0] $end
$var reg 1 = frame_error $end
$var reg 1 $ irq $end
$var reg 16 > rx_baud_counter [15:0] $end
$var reg 3 ? rx_bit_counter [2:0] $end
$var reg 8 @ rx_data [7:0] $end
$var reg 1 A rx_enable $end
$var reg 1 B rx_int_en $end
$var reg 1 C rx_overrun $end
$var reg 1 D rx_ready $end
$var reg 8 E rx_shift_reg [7:0] $end
$var reg 2 F rx_state [1:0] $end
$var reg 16 G tx_baud_counter [15:0] $end
$var reg 3 H tx_bit_counter [2:0] $end
$var reg 8 I tx_data [7:0] $end
$var reg 1 J tx_empty $end
$var reg 1 K tx_enable $end
$var reg 8 L tx_shift_reg [7:0] $end
$var reg 1 M tx_start $end
$var reg 2 N tx_state [1:0] $end
$var reg 1 O uart_rx_sync1 $end
$var reg 1 P uart_rx_sync2 $end
$var reg 1 # uart_tx $end
$var reg 1 " wb_ack $end
$var reg 32 Q wb_dat_o [31:0] $end
$upscope $end
$upscope $end
$enddefinitions $end
$comment Show the parameter values. $end
$dumpall
b11 ;
b1 :
b0 9
b10 8
b11 7
b1 6
b0 5
b10 4
b110110010 3
b11100001000000000 2
b10111110101111000010000000 1
b1000 0
$end
#0
$dumpvars
b0 Q
1P
1O
b0 N
0M
b0 L
1K
1J
b0 I
b0 H
b0 G
b0 F
b0 E
0D
0C
0B
1A
b0 @
b0 ?
b0 >
0=
b110110010 <
b1111 /
b0 .
b0 -
1,
0+
0*
b1111 )
b0 (
b0 '
0&
0%
0$
1#
0"
b0 !
$end
#10000
1%
#20000
0%
#30000
1%
#40000
0%
#50000
1%
#60000
0%
#70000
1%
#80000
0%
#90000
1%
#100000
0%
1&
#110000
1%
#120000
0%
#130000
1%
#140000
0%
#150000
1%
#160000
0%
#170000
1%
#180000
0%
#190000
1%
#200000
0%
#210000
1M
b1001000 I
1"
1*
1+
b1001000 (
b1001000 .
1%
#220000
0%
#230000
0J
b1001000 L
b1 N
0M
0"
0+
0*
1%
#240000
0%
#250000
b1 G
0#
1%
#260000
0%
#270000
b10 G
1%
#280000
0%
#290000
b11 G
1%
#300000
0%
#310000
b100 G
1%
#320000
0%
#330000
b101 G
1%
#340000
0%
#350000
b110 G
1%
#360000
0%
#370000
b111 G
1%
#380000
0%
#390000
b1000 G
1%
#400000
0%
#410000
b1001 G
1%
#420000
0%
#430000
b1010 G
1%
#440000
0%
#450000
b1011 G
1%
#460000
0%
#470000
b1100 G
1%
#480000
0%
#490000
b1101 G
1%
#500000
0%
#510000
b1110 G
1%
#520000
0%
#530000
b1111 G
1%
#540000
0%
#550000
b10000 G
1%
#560000
0%
#570000
b10001 G
1%
#580000
0%
#590000
b10010 G
1%
#600000
0%
#610000
b10011 G
1%
#620000
0%
#630000
b10100 G
1%
#640000
0%
#650000
b10101 G
1%
#660000
0%
#670000
b10110 G
1%
#680000
0%
#690000
b10111 G
1%
#700000
0%
#710000
b11000 G
1%
#720000
0%
#730000
b11001 G
1%
#740000
0%
#750000
b11010 G
1%
#760000
0%
#770000
b11011 G
1%
#780000
0%
#790000
b11100 G
1%
#800000
0%
#810000
b11101 G
1%
#820000
0%
#830000
b11110 G
1%
#840000
0%
#850000
b11111 G
1%
#860000
0%
#870000
b100000 G
1%
#880000
0%
#890000
b100001 G
1%
#900000
0%
#910000
b100010 G
1%
#920000
0%
#930000
b100011 G
1%
#940000
0%
#950000
b100100 G
1%
#960000
0%
#970000
b100101 G
1%
#980000
0%
#990000
b100110 G
1%
#1000000
0%
#1010000
b100111 G
1%
#1020000
0%
#1030000
b101000 G
1%
#1040000
0%
#1050000
b101001 G
1%
#1060000
0%
#1070000
b101010 G
1%
#1080000
0%
#1090000
b101011 G
1%
#1100000
0%
#1110000
b101100 G
1%
#1120000
0%
#1130000
b101101 G
1%
#1140000
0%
#1150000
b101110 G
1%
#1160000
0%
#1170000
b101111 G
1%
#1180000
0%
#1190000
b110000 G
1%
#1200000
0%
#1210000
b110001 G
1%
#1220000
0%
#1230000
b110010 G
1%
#1240000
0%
#1250000
b110011 G
1%
#1260000
0%
#1270000
b110100 G
1%
#1280000
0%
#1290000
b110101 G
1%
#1300000
0%
#1310000
b110110 G
1%
#1320000
0%
#1330000
b110111 G
1%
#1340000
0%
#1350000
b111000 G
1%
#1360000
0%
#1370000
b111001 G
1%
#1380000
0%
#1390000
b111010 G
1%
#1400000
0%
#1410000
b111011 G
1%
#1420000
0%
#1430000
b111100 G
1%
#1440000
0%
#1450000
b111101 G
1%
#1460000
0%
#1470000
b111110 G
1%
#1480000
0%
#1490000
b111111 G
1%
#1500000
0%
#1510000
b1000000 G
1%
#1520000
0%
#1530000
b1000001 G
1%
#1540000
0%
#1550000
b1000010 G
1%
#1560000
0%
#1570000
b1000011 G
1%
#1580000
0%
#1590000
b1000100 G
1%
#1600000
0%
#1610000
b1000101 G
1%
#1620000
0%
#1630000
b1000110 G
1%
#1640000
0%
#1650000
b1000111 G
1%
#1660000
0%
#1670000
b1001000 G
1%
#1680000
0%
#1690000
b1001001 G
1%
#1700000
0%
#1710000
b1001010 G
1%
#1720000
0%
#1730000
b1001011 G
1%
#1740000
0%
#1750000
b1001100 G
1%
#1760000
0%
#1770000
b1001101 G
1%
#1780000
0%
#1790000
b1001110 G
1%
#1800000
0%
#1810000
b1001111 G
1%
#1820000
0%
#1830000
b1010000 G
1%
#1840000
0%
#1850000
b1010001 G
1%
#1860000
0%
#1870000
b1010010 G
1%
#1880000
0%
#1890000
b1010011 G
1%
#1900000
0%
#1910000
b1010100 G
1%
#1920000
0%
#1930000
b1010101 G
1%
#1940000
0%
#1950000
b1010110 G
1%
#1960000
0%
#1970000
b1010111 G
1%
#1980000
0%
#1990000
b1011000 G
1%
#2000000
0%
#2010000
b1011001 G
1%
#2020000
0%
#2030000
b1011010 G
1%
#2040000
0%
#2050000
b1011011 G
1%
#2060000
0%
#2070000
b1011100 G
1%
#2080000
0%
#2090000
b1011101 G
1%
#2100000
0%
#2110000
b1011110 G
1%
#2120000
0%
#2130000
b1011111 G
1%
#2140000
0%
#2150000
b1100000 G
1%
#2160000
0%
#2170000
b1100001 G
1%
#2180000
0%
#2190000
b1100010 G
1%
#2200000
0%
#2210000
b1100011 G
1%
#2220000
0%
#2230000
b1100100 G
1%
#2240000
0%
#2250000
b1100101 G
1%
#2260000
0%
#2270000
b1100110 G
1%
#2280000
0%
#2290000
b1100111 G
1%
#2300000
0%
#2310000
b1101000 G
1%
#2320000
0%
#2330000
b1101001 G
1%
#2340000
0%
#2350000
b1101010 G
1%
#2360000
0%
#2370000
b1101011 G
1%
#2380000
0%
#2390000
b1101100 G
1%
#2400000
0%
#2410000
b1101101 G
1%
#2420000
0%
#2430000
b1101110 G
1%
#2440000
0%
#2450000
b1101111 G
1%
#2460000
0%
#2470000
b1110000 G
1%
#2480000
0%
#2490000
b1110001 G
1%
#2500000
0%
#2510000
b1110010 G
1%
#2520000
0%
#2530000
b1110011 G
1%
#2540000
0%
#2550000
b1110100 G
1%
#2560000
0%
#2570000
b1110101 G
1%
#2580000
0%
#2590000
b1110110 G
1%
#2600000
0%
#2610000
b1110111 G
1%
#2620000
0%
#2630000
b1111000 G
1%
#2640000
0%
#2650000
b1111001 G
1%
#2660000
0%
#2670000
b1111010 G
1%
#2680000
0%
#2690000
b1111011 G
1%
#2700000
0%
#2710000
b1111100 G
1%
#2720000
0%
#2730000
b1111101 G
1%
#2740000
0%
#2750000
b1111110 G
1%
#2760000
0%
#2770000
b1111111 G
1%
#2780000
0%
#2790000
b10000000 G
1%
#2800000
0%
#2810000
b10000001 G
1%
#2820000
0%
#2830000
b10000010 G
1%
#2840000
0%
#2850000
b10000011 G
1%
#2860000
0%
#2870000
b10000100 G
1%
#2880000
0%
#2890000
b10000101 G
1%
#2900000
0%
#2910000
b10000110 G
1%
#2920000
0%
#2930000
b10000111 G
1%
#2940000
0%
#2950000
b10001000 G
1%
#2960000
0%
#2970000
b10001001 G
1%
#2980000
0%
#2990000
b10001010 G
1%
#3000000
0%
#3010000
b10001011 G
1%
#3020000
0%
#3030000
b10001100 G
1%
#3040000
0%
#3050000
b10001101 G
1%
#3060000
0%
#3070000
b10001110 G
1%
#3080000
0%
#3090000
b10001111 G
1%
#3100000
0%
#3110000
b10010000 G
1%
#3120000
0%
#3130000
b10010001 G
1%
#3140000
0%
#3150000
b10010010 G
1%
#3160000
0%
#3170000
b10010011 G
1%
#3180000
0%
#3190000
b10010100 G
1%
#3200000
0%
#3210000
b10010101 G
1%
#3220000
0%
#3230000
b10010110 G
1%
#3240000
0%
#3250000
b10010111 G
1%
#3260000
0%
#3270000
b10011000 G
1%
#3280000
0%
#3290000
b10011001 G
1%
#3300000
0%
#3310000
b10011010 G
1%
#3320000
0%
#3330000
b10011011 G
1%
#3340000
0%
#3350000
b10011100 G
1%
#3360000
0%
#3370000
b10011101 G
1%
#3380000
0%
#3390000
b10011110 G
1%
#3400000
0%
#3410000
b10011111 G
1%
#3420000
0%
#3430000
b10100000 G
1%
#3440000
0%
#3450000
b10100001 G
1%
#3460000
0%
#3470000
b10100010 G
1%
#3480000
0%
#3490000
b10100011 G
1%
#3500000
0%
#3510000
b10100100 G
1%
#3520000
0%
#3530000
b10100101 G
1%
#3540000
0%
#3550000
b10100110 G
1%
#3560000
0%
#3570000
b10100111 G
1%
#3580000
0%
#3590000
b10101000 G
1%
#3600000
0%
#3610000
b10101001 G
1%
#3620000
0%
#3630000
b10101010 G
1%
#3640000
0%
#3650000
b10101011 G
1%
#3660000
0%
#3670000
b10101100 G
1%
#3680000
0%
#3690000
b10101101 G
1%
#3700000
0%
#3710000
b10101110 G
1%
#3720000
0%
#3730000
b10101111 G
1%
#3740000
0%
#3750000
b10110000 G
1%
#3760000
0%
#3770000
b10110001 G
1%
#3780000
0%
#3790000
b10110010 G
1%
#3800000
0%
#3810000
b10110011 G
1%
#3820000
0%
#3830000
b10110100 G
1%
#3840000
0%
#3850000
b10110101 G
1%
#3860000
0%
#3870000
b10110110 G
1%
#3880000
0%
#3890000
b10110111 G
1%
#3900000
0%
#3910000
b10111000 G
1%
#3920000
0%
#3930000
b10111001 G
1%
#3940000
0%
#3950000
b10111010 G
1%
#3960000
0%
#3970000
b10111011 G
1%
#3980000
0%
#3990000
b10111100 G
1%
#4000000
0%
#4010000
b10111101 G
1%
#4020000
0%
#4030000
b10111110 G
1%
#4040000
0%
#4050000
b10111111 G
1%
#4060000
0%
#4070000
b11000000 G
1%
#4080000
0%
#4090000
b11000001 G
1%
#4100000
0%
#4110000
b11000010 G
1%
#4120000
0%
#4130000
b11000011 G
1%
#4140000
0%
#4150000
b11000100 G
1%
#4160000
0%
#4170000
b11000101 G
1%
#4180000
0%
#4190000
b11000110 G
1%
#4200000
0%
#4210000
b11000111 G
1%
#4220000
0%
#4230000
b11001000 G
1%
#4240000
0%
#4250000
b11001001 G
1%
#4260000
0%
#4270000
b11001010 G
1%
#4280000
0%
#4290000
b11001011 G
1%
#4300000
0%
#4310000
b11001100 G
1%
#4320000
0%
#4330000
b11001101 G
1%
#4340000
0%
#4350000
b11001110 G
1%
#4360000
0%
#4370000
b11001111 G
1%
#4380000
0%
#4390000
b11010000 G
1%
#4400000
0%
#4410000
b11010001 G
1%
#4420000
0%
#4430000
b11010010 G
1%
#4440000
0%
#4450000
b11010011 G
1%
#4460000
0%
#4470000
b11010100 G
1%
#4480000
0%
#4490000
b11010101 G
1%
#4500000
0%
#4510000
b11010110 G
1%
#4520000
0%
#4530000
b11010111 G
1%
#4540000
0%
#4550000
b11011000 G
1%
#4560000
0%
#4570000
b11011001 G
1%
#4580000
0%
#4590000
b11011010 G
1%
#4600000
0%
#4610000
b11011011 G
1%
#4620000
0%
#4630000
b11011100 G
1%
#4640000
0%
#4650000
b11011101 G
1%
#4660000
0%
#4670000
b11011110 G
1%
#4680000
0%
#4690000
b11011111 G
1%
#4700000
0%
#4710000
b11100000 G
1%
#4720000
0%
#4730000
b11100001 G
1%
#4740000
0%
#4750000
b11100010 G
1%
#4760000
0%
#4770000
b11100011 G
1%
#4780000
0%
#4790000
b11100100 G
1%
#4800000
0%
#4810000
b11100101 G
1%
#4820000
0%
#4830000
b11100110 G
1%
#4840000
0%
#4850000
b11100111 G
1%
#4860000
0%
#4870000
b11101000 G
1%
#4880000
0%
#4890000
b11101001 G
1%
#4900000
0%
#4910000
b11101010 G
1%
#4920000
0%
#4930000
b11101011 G
1%
#4940000
0%
#4950000
b11101100 G
1%
#4960000
0%
#4970000
b11101101 G
1%
#4980000
0%
#4990000
b11101110 G
1%
#5000000
0%
#5010000
b11101111 G
1%
#5020000
0%
#5030000
b11110000 G
1%
#5040000
0%
#5050000
b11110001 G
1%
#5060000
0%
#5070000
b11110010 G
1%
#5080000
0%
#5090000
b11110011 G
1%
#5100000
0%
#5110000
b11110100 G
1%
#5120000
0%
#5130000
b11110101 G
1%
#5140000
0%
#5150000
b11110110 G
1%
#5160000
0%
#5170000
b11110111 G
1%
#5180000
0%
#5190000
b11111000 G
1%
#5200000
0%
#5210000
b11111001 G
1%
#5220000
0%
#5230000
b11111010 G
1%
#5240000
0%
#5250000
b11111011 G
1%
#5260000
0%
#5270000
b11111100 G
1%
#5280000
0%
#5290000
b11111101 G
1%
#5300000
0%
#5310000
b11111110 G
1%
#5320000
0%
#5330000
b11111111 G
1%
#5340000
0%
#5350000
b100000000 G
1%
#5360000
0%
#5370000
b100000001 G
1%
#5380000
0%
#5390000
b100000010 G
1%
#5400000
0%
#5410000
b100000011 G
1%
#5420000
0%
#5430000
b100000100 G
1%
#5440000
0%
#5450000
b100000101 G
1%
#5460000
0%
#5470000
b100000110 G
1%
#5480000
0%
#5490000
b100000111 G
1%
#5500000
0%
#5510000
b100001000 G
1%
#5520000
0%
#5530000
b100001001 G
1%
#5540000
0%
#5550000
b100001010 G
1%
#5560000
0%
#5570000
b100001011 G
1%
#5580000
0%
#5590000
b100001100 G
1%
#5600000
0%
#5610000
b100001101 G
1%
#5620000
0%
#5630000
b100001110 G
1%
#5640000
0%
#5650000
b100001111 G
1%
#5660000
0%
#5670000
b100010000 G
1%
#5680000
0%
#5690000
b100010001 G
1%
#5700000
0%
#5710000
b100010010 G
1%
#5720000
0%
#5730000
b100010011 G
1%
#5740000
0%
#5750000
b100010100 G
1%
#5760000
0%
#5770000
b100010101 G
1%
#5780000
0%
#5790000
b100010110 G
1%
#5800000
0%
#5810000
b100010111 G
1%
#5820000
0%
#5830000
b100011000 G
1%
#5840000
0%
#5850000
b100011001 G
1%
#5860000
0%
#5870000
b100011010 G
1%
#5880000
0%
#5890000
b100011011 G
1%
#5900000
0%
#5910000
b100011100 G
1%
#5920000
0%
#5930000
b100011101 G
1%
#5940000
0%
#5950000
b100011110 G
1%
#5960000
0%
#5970000
b100011111 G
1%
#5980000
0%
#5990000
b100100000 G
1%
#6000000
0%
#6010000
b100100001 G
1%
#6020000
0%
#6030000
b100100010 G
1%
#6040000
0%
#6050000
b100100011 G
1%
#6060000
0%
#6070000
b100100100 G
1%
#6080000
0%
#6090000
b100100101 G
1%
#6100000
0%
#6110000
b100100110 G
1%
#6120000
0%
#6130000
b100100111 G
1%
#6140000
0%
#6150000
b100101000 G
1%
#6160000
0%
#6170000
b100101001 G
1%
#6180000
0%
#6190000
b100101010 G
1%
#6200000
0%
#6210000
b100101011 G
1%
#6220000
0%
#6230000
b100101100 G
1%
#6240000
0%
#6250000
b100101101 G
1%
#6260000
0%
#6270000
b100101110 G
1%
#6280000
0%
#6290000
b100101111 G
1%
#6300000
0%
#6310000
b100110000 G
1%
#6320000
0%
#6330000
b100110001 G
1%
#6340000
0%
#6350000
b100110010 G
1%
#6360000
0%
#6370000
b100110011 G
1%
#6380000
0%
#6390000
b100110100 G
1%
#6400000
0%
#6410000
b100110101 G
1%
#6420000
0%
#6430000
b100110110 G
1%
#6440000
0%
#6450000
b100110111 G
1%
#6460000
0%
#6470000
b100111000 G
1%
#6480000
0%
#6490000
b100111001 G
1%
#6500000
0%
#6510000
b100111010 G
1%
#6520000
0%
#6530000
b100111011 G
1%
#6540000
0%
#6550000
b100111100 G
1%
#6560000
0%
#6570000
b100111101 G
1%
#6580000
0%
#6590000
b100111110 G
1%
#6600000
0%
#6610000
b100111111 G
1%
#6620000
0%
#6630000
b101000000 G
1%
#6640000
0%
#6650000
b101000001 G
1%
#6660000
0%
#6670000
b101000010 G
1%
#6680000
0%
#6690000
b101000011 G
1%
#6700000
0%
#6710000
b101000100 G
1%
#6720000
0%
#6730000
b101000101 G
1%
#6740000
0%
#6750000
b101000110 G
1%
#6760000
0%
#6770000
b101000111 G
1%
#6780000
0%
#6790000
b101001000 G
1%
#6800000
0%
#6810000
b101001001 G
1%
#6820000
0%
#6830000
b101001010 G
1%
#6840000
0%
#6850000
b101001011 G
1%
#6860000
0%
#6870000
b101001100 G
1%
#6880000
0%
#6890000
b101001101 G
1%
#6900000
0%
#6910000
b101001110 G
1%
#6920000
0%
#6930000
b101001111 G
1%
#6940000
0%
#6950000
b101010000 G
1%
#6960000
0%
#6970000
b101010001 G
1%
#6980000
0%
#6990000
b101010010 G
1%
#7000000
0%
#7010000
b101010011 G
1%
#7020000
0%
#7030000
b101010100 G
1%
#7040000
0%
#7050000
b101010101 G
1%
#7060000
0%
#7070000
b101010110 G
1%
#7080000
0%
#7090000
b101010111 G
1%
#7100000
0%
#7110000
b101011000 G
1%
#7120000
0%
#7130000
b101011001 G
1%
#7140000
0%
#7150000
b101011010 G
1%
#7160000
0%
#7170000
b101011011 G
1%
#7180000
0%
#7190000
b101011100 G
1%
#7200000
0%
#7210000
b101011101 G
1%
#7220000
0%
#7230000
b101011110 G
1%
#7240000
0%
#7250000
b101011111 G
1%
